ytb_downloader/__init__.py
ytb_downloader/config.py
ytb_downloader/constants.py
ytb_downloader/converter.py
ytb_downloader/downloader.py
ytb_downloader/file_loader.py
ytb_downloader/file_name_collector.py
ytb_downloader/main.py
ytb_downloader-0.4.0.dist-info/LICENSE
ytb_downloader-0.4.0.dist-info/METADATA
ytb_downloader-0.4.0.dist-info/WHEEL
ytb_downloader-0.4.0.dist-info/entry_points.txt
ytb_downloader-0.4.0.dist-info/RECORD
