Metadata-Version: 2.1
Name: ytb_downloader
Version: 0.4.0
Summary: Download youtube videos and convert them to mp3.
Home-page: https://github.com/zhiwei2017/ytb_downloader
License: MIT
Author: Zhiwei Zhang
Author-email: zhiwei2017@gmail.com
Requires-Python: >=3.9,<4.0
Classifier: License :: OSI Approved :: MIT License
Classifier: Programming Language :: Python :: 3
Classifier: Programming Language :: Python :: 3.9
Classifier: Programming Language :: Python :: 3.10
Classifier: Programming Language :: Python :: 3.11
Classifier: Programming Language :: Python :: 3.12
Classifier: Programming Language :: Python :: 3.13
Requires-Dist: click (>=8.1,<8.2)
Requires-Dist: moviepy (>=1.0,<1.1)
Requires-Dist: pandas (>=2.2,<2.3)
Requires-Dist: pydantic (>=2.9,<2.10)
Requires-Dist: pydantic-settings (>=2.6,<2.7)
Requires-Dist: yt-dlp (==2024.11.4)
Project-URL: Documentation, https://zhiwei2017.github.io/ytb_downloader/
Project-URL: Repository, https://github.com/zhiwei2017/ytb_downloader
